addresscomplete/AddressComplete.py
addresscomplete/ErrorHandling.py
addresscomplete/__init__.py
addresscomplete-1.0.3.dist-info/METADATA
addresscomplete-1.0.3.dist-info/WHEEL
addresscomplete-1.0.3.dist-info/licenses/LICENSE
addresscomplete-1.0.3.dist-info/RECORD
