Metadata-Version: 2.4
Name: addresscomplete
Version: 1.0.3
Summary: A Python client for the Canada Post AddressComplete API
Project-URL: Repository, https://github.com/darianelwood/AddressComplete
Project-URL: Issues, https://github.com/darianelwood/AddressComplete/issues
Author-email: Darian Elwood <dellwood546@gmail.com>
License: GPL-3.0
License-File: LICENSE
Keywords: address,address-autocomplete,address-validation,addresscomplete,canada-post
Classifier: Development Status :: 5 - Production/Stable
Classifier: Intended Audience :: Developers
Classifier: License :: OSI Approved :: GNU General Public License v3 (GPLv3)
Classifier: Programming Language :: Python :: 3
Classifier: Programming Language :: Python :: 3.7
Classifier: Programming Language :: Python :: 3.8
Classifier: Programming Language :: Python :: 3.9
Classifier: Programming Language :: Python :: 3.10
Classifier: Programming Language :: Python :: 3.11
Classifier: Programming Language :: Python :: 3.12
Classifier: Topic :: Software Development :: Libraries :: Python Modules
Requires-Python: >=3.7
Requires-Dist: requests>=2.32.3
